allure_markdown/__init__.py
allure_markdown/__version__.py
allure_markdown/cli.py
allure_markdown/config.py
allure_markdown/main.py
allure_markdown/pytest_plugin.py
allure_markdown/templates/report.md.j2
allure_markdown-1.6.1.dist-info/METADATA
allure_markdown-1.6.1.dist-info/WHEEL
allure_markdown-1.6.1.dist-info/entry_points.txt
allure_markdown-1.6.1.dist-info/licenses/LICENSE
allure_markdown-1.6.1.dist-info/RECORD
