Metadata-Version: 2.4
Name: allure-markdown
Version: 1.6.1
Summary: 将 Allure 的元数据转换为 Markdown 格式的报告
Author-email: mikigo <mikigo@foxmail.com>
License: Apache2.0
License-File: LICENSE
Requires-Python: >=3.6
Requires-Dist: click
Requires-Dist: jinja2
